VLSILabCourse/4BitRCA/full_adder.v
// Module: 1 bit full adder

module full_adder(in_1, in_2, c_in, sum, c_out);

    input in_1, in_2, c_in;
    output sum, c_out;

    assign sum = in_1 ^ in_2 ^ c_in;
    assign c_out = in_1 & in_2 | in_1 & c_in | in_2 & c_in;

endmodule

VLSILabCourse/1BitFA/FullAdder_tb.v
`timescale 1ns / 1ns
`include "FullAdder.v"

module full_adder_tb;

    reg A, B, Cin;
    wire Sum, Wire;

    full_adder uut(
        .in_1(A),
        .in_2(B),
        .c_in(Cin),
        .sum(Sum),
        .c_out(Cout)
    );

    initial begin

        $dumpfile("full_adder_tb.vcd");
        $dumpvars(0, full_adder_tb);

        A = 1'b0; B = 1'b0; Cin = 1'b0;
        #200;

        $display("Simulations complete, results are ready");
        $finish;

    end

    always begin

        #25; A = ~A;

    end

    always begin

        #50; B = ~B;

    end

    always begin

        #75; Cin = ~Cin;

    end


endmodule

VLSILabCourse/1BitFA/full_adder_tb.vcd
$date
	Fri Sep 27 00:37:51 2024
$end
$version
	Icarus Verilog
$end
$timescale
	1ns
$end
$scope module full_adder_tb $end
$var wire 1 ! Sum $end
$var wire 1 " Cout $end
$var reg 1 # A $end
$var reg 1 $ B $end
$var reg 1 % Cin $end
$scope module uut $end
$var wire 1 % c_in $end
$var wire 1 " c_out $end
$var wire 1 # in_1 $end
$var wire 1 $ in_2 $end
$var wire 1 ! sum $end
$upscope $end
$upscope $end
$enddefinitions $end
#0
$dumpvars
0%
0$
0#
0"
0!
$end
#25
1!
1#
#50
0#
1$
#75
1"
1!
1#
1%
#100
0"
0#
0$
#125
1"
0!
1#
#150
0"
1!
0#
1$
0%
#175
1"
0!
1#
#200
0"
0#
0$
