VLSILabCourse/4BitRCA/full_adder.v
// Module: 1 bit full adder

module full_adder(in_1, in_2, c_in, sum, c_out);

    input in_1, in_2, c_in;
    output sum, c_out;

    assign sum = in_1 ^ in_2 ^ c_in;
    assign c_out = in_1 & in_2 | in_1 & c_in | in_2 & c_in;

endmodule

VLSILabCourse/4BitRCA/ripple_carry_adder.v
// Module: 4-bit ripple carry adder
`include "full_adder.v"

module ripple_carry_adder(in_1, in_2, c_in, sum, c_out);

    input [3:0] in_1;
    input [3:0] in_2;
    input c_in;

    output [3:0] sum;
    output c_out;

    wire c1, c2, c3;

    full_adder fa1(.in_1(in_1[0]), .in_2(in_2[0]), .c_in(c_in), .sum(sum[0]), .c_out(c1));
    full_adder fa2(.in_1(in_1[1]), .in_2(in_2[1]), .c_in(c1), .sum(sum[1]), .c_out(c2));
    full_adder fa3(.in_1(in_1[2]), .in_2(in_2[2]), .c_in(c2), .sum(sum[2]), .c_out(c3));
    full_adder fa4(.in_1(in_1[3]), .in_2(in_2[3]), .c_in(c3), .sum(sum[3]), .c_out(c_out));

endmodule

VLSILabCourse/4BitRCA/ripple_carry_adder_tb.v
`timescale 1ns / 1ns
`include "ripple_carry_adder.v"

module ripple_carry_adder_tb;

    reg [3:0] A;
    reg [3:0] B;
    reg Cin;

    wire [3:0] Sum;
    wire Cout;

    ripple_carry_adder uut(

        .in_1(A),
        .in_2(B),
        .c_in(Cin),
        .sum(Sum),
        .c_out(Cout)
    );

    initial begin

        $dumpfile("ripple_carry_adder_tb.vcd");
        $dumpvars(0, ripple_carry_adder_tb);

        A = 4'b0001; B = 4'b1111; Cin = 1'b1; #25;
        A = 4'b0101; B = 4'b1101; Cin = 1'b0; #25;
        A = 4'b1001; B = 4'b1011; Cin = 1'b1; #25;
        A = 4'b0101; B = 4'b1000; Cin = 1'b1; #25;
        A = 4'b0011; B = 4'b1110; Cin = 1'b0; #25;
        A = 4'b1001; B = 4'b1100; Cin = 1'b0; #25;
        A = 4'b0111; B = 4'b1011; Cin = 1'b1; #25;
        A = 4'b1111; B = 4'b0001; Cin = 1'b1; #25;
        A = 4'b0011; B = 4'b1001; Cin = 1'b1; #25;
        A = 4'b1001; B = 4'b1101; Cin = 1'b0; #25;
        A = 4'b0101; B = 4'b0011; Cin = 1'b1; #25;
        A = 4'b1001; B = 4'b1010; Cin = 1'b1; #25;
        A = 4'b0010; B = 4'b1000; Cin = 1'b1; #25;
        A = 4'b0011; B = 4'b1101; Cin = 1'b0; #25;
        A = 4'b1000; B = 4'b0100; Cin = 1'b1; #25;

        $display("Simulations complete, results are ready.");
        $finish;
    
    end

endmodule

VLSILabCourse/4BitRCA/ripple_carry_adder_tb.vcd
$date
	Fri Sep 27 01:28:38 2024
$end
$version
	Icarus Verilog
$end
$timescale
	1ns
$end
$scope module ripple_carry_adder_tb $end
$var wire 4 ! Sum [3:0] $end
$var wire 1 " Cout $end
$var reg 4 # A [3:0] $end
$var reg 4 $ B [3:0] $end
$var reg 1 % Cin $end
$scope module uut $end
$var wire 1 % c_in $end
$var wire 4 & in_1 [3:0] $end
$var wire 4 ' in_2 [3:0] $end
$var wire 4 ( sum [3:0] $end
$var wire 1 " c_out $end
$var wire 1 ) c3 $end
$var wire 1 * c2 $end
$var wire 1 + c1 $end
$scope module fa1 $end
$var wire 1 % c_in $end
$var wire 1 + c_out $end
$var wire 1 , in_1 $end
$var wire 1 - in_2 $end
$var wire 1 . sum $end
$upscope $end
$scope module fa2 $end
$var wire 1 + c_in $end
$var wire 1 * c_out $end
$var wire 1 / in_1 $end
$var wire 1 0 in_2 $end
$var wire 1 1 sum $end
$upscope $end
$scope module fa3 $end
$var wire 1 * c_in $end
$var wire 1 ) c_out $end
$var wire 1 2 in_1 $end
$var wire 1 3 in_2 $end
$var wire 1 4 sum $end
$upscope $end
$scope module fa4 $end
$var wire 1 ) c_in $end
$var wire 1 " c_out $end
$var wire 1 5 in_1 $end
$var wire 1 6 in_2 $end
$var wire 1 7 sum $end
$upscope $end
$upscope $end
$upscope $end
$enddefinitions $end
#0
$dumpvars
07
16
05
04
13
02
01
10
0/
1.
1-
1,
1+
1*
1)
b1 (
b1111 '
b1 &
1%
b1111 $
b1 #
1"
b1 !
$end
#25
11
0*
04
b10 !
b10 (
0.
00
12
0%
b1101 $
b1101 '
b101 #
b101 &
#50
14
0)
01
1*
07
b101 !
b101 (
1.
10
03
02
15
1%
b1011 $
b1011 '
b1001 #
b1001 &
#75
0)
0"
0.
11
0*
14
b1110 !
b1110 (
17
0-
00
12
05
b1000 $
b1000 '
b101 #
b101 &
#100
1"
07
1)
01
04
0+
1*
b1 !
b1 (
1.
10
13
1/
02
0%
b1110 $
b1110 '
b11 #
b11 &
#125
0)
14
0*
b101 !
b101 (
07
00
0/
15
b1100 $
b1100 '
b1001 #
b1001 &
#150
1)
04
1*
1"
11
07
1+
b11 !
b11 (
1.
1-
10
03
1/
12
05
1%
b1011 $
b1011 '
b111 #
b111 &
#175
b1 !
b1 (
01
00
06
15
b1 $
b1 '
b1111 #
b1111 &
#200
0"
17
0)
b1101 !
b1101 (
14
16
02
05
b1001 $
b1001 '
b11 #
b11 &
#225
0*
1"
14
0)
11
07
b110 !
b110 (
0.
13
0/
15
0%
b1101 $
b1101 '
b1001 #
b1001 &
#250
17
1)
04
0"
01
1*
b1001 !
b1001 (
1.
10
03
06
12
05
1%
b11 $
b11 '
b101 #
b101 &
#275
07
0)
0.
1"
b100 !
b100 (
14
0-
16
02
15
b1010 $
b1010 '
b1001 #
b1001 &
#300
04
0*
11
0+
0"
1.
b1011 !
b1011 (
17
00
0,
1/
05
b1000 $
b1000 '
b10 #
b10 &
#325
1"
07
1)
1*
01
1+
04
b0 !
b0 (
0.
1-
13
1,
0%
b1101 $
b1101 '
b11 #
b11 &
#350
0"
17
0)
14
0+
0*
01
b1101 !
b1101 (
1.
0-
06
0,
0/
15
1%
b100 $
b100 '
b1000 #
b1000 &
