SwitchLevelModelling/CMOSNor/CMOSNor.v
// CMOS Nor Gate

module CMOSNor(in_1, in_2, out);

	// Declaring the ports
	input in_1, in_2;
	output out;

	// Declaring the power supply
	supply1 vdd;
	supply0 gnd;

	// Interconnects
	wire connect1;

	// Nor Gate Body
	nmos n1(out, gnd, in_1);
	nmos n2(out, gnd, in_2);

	pmos p1(out, connect1, in_1);
	pmos p2(connect1, vdd, in_2);

endmodule

SwitchLevelModelling/CMOSNor/CMOSNor_tb.v
`timescale 1ns / 1ns
`include "CMOSNor.v"

module CMOSNor_tb;

	reg A, B, clk, rst;
	wire Out;

	CMOSNor uut(
		.in_1(A),
		.in_2(B),
		.out(Out)
	);

	initial begin
		$dumpfile("CMOSNor_tb.vcd");
		$dumpvars(0, CMOSNor_tb);

		clk <= 0;
		rst <= 0;
		A <= 0;
		B <= 0;
		#10;
		rst <= 1;
		#120;
		rst <= 0;
	end

	always begin
		clk = ~clk;
		#10;
	end

	always@(posedge clk, posedge rst) begin
		
		if (rst) begin
			A <= 0;
			B <= 0;
		end

		else begin
			A <= 0;
			B <= 1;
			#20;

			A <= 1;
			B <= 0;
			#20;

			B <= 1;
			#20;

			A <= 0;
			B <= 0;
			#20;

			B <= 1;
			#20;

			A <= 1;
			B <= 0;
			#20;

			B <= 1;
			#20;

			$display("Simulation complete, results are ready.");
			$finish;
		end

	end

	always@(negedge rst) begin
		A <= 0;
		B <= 0;
	end

endmodule

SwitchLevelModelling/CMOSNor/CMOSNor_tb.vcd
$date
	Wed May  8 13:28:07 2024
$end
$version
	Icarus Verilog
$end
$timescale
	1ns
$end
$scope module CMOSNor_tb $end
$var wire 1 ! Out $end
$var reg 1 " A $end
$var reg 1 # B $end
$var reg 1 $ clk $end
$var reg 1 % rst $end
$scope module uut $end
$var wire 1 & connect1 $end
$var wire 1 ' gnd $end
$var wire 1 " in_1 $end
$var wire 1 # in_2 $end
$var wire 1 ! out $end
$var wire 1 ( vdd $end
$upscope $end
$upscope $end
$enddefinitions $end
#0
$dumpvars
1(
0'
1&
0%
0$
0#
0"
1!
$end
#10
0!
z&
1#
1%
1$
#20
0$
#30
1&
0#
1"
1$
#40
0$
#50
z&
1#
1$
#60
0$
#70
1!
1&
0#
0"
1$
#80
0$
#90
0!
z&
1#
1$
#100
0$
#110
1&
0#
1"
1$
#120
0$
#130
1!
0"
1&
0#
0%
1$
